nemseer/__init__.py
nemseer/data.py
nemseer/data_compilers.py
nemseer/data_handlers.py
nemseer/downloader.py
nemseer/forecast_type/__init__.py
nemseer/forecast_type/run_time_generators.py
nemseer/forecast_type/validators.py
nemseer/nemseer.py
nemseer/py.typed
nemseer/query.py
nemseer-1.0.6.dist-info/LICENSE
nemseer-1.0.6.dist-info/METADATA
nemseer-1.0.6.dist-info/WHEEL
nemseer-1.0.6.dist-info/RECORD
