Metadata-Version: 2.1
Name: nemseer
Version: 1.0.6
Summary: A package for downloading and handling forecasts for the National Electricity Market (NEM) from the Australian Energy Market Operator (AEMO).
License: GPL-3.0-or-later
Author: Abhijith Prakash
Requires-Python: >=3.8,<3.12
Classifier: License :: OSI Approved :: GNU General Public License v3 or later (GPLv3+)
Classifier: Programming Language :: Python :: 3
Classifier: Programming Language :: Python :: 3.8
Classifier: Programming Language :: Python :: 3.9
Classifier: Programming Language :: Python :: 3.10
Classifier: Programming Language :: Python :: 3.11
Requires-Dist: attrs (>=21,<22)
Requires-Dist: beautifulsoup4
Requires-Dist: netCDF4 (>=1,<2)
Requires-Dist: numpy
Requires-Dist: packaging (>=21.3,<22.0)
Requires-Dist: pandas
Requires-Dist: psutil (>=5,<6)
Requires-Dist: pyarrow
Requires-Dist: requests (>=2,<3)
Requires-Dist: tqdm (>=4,<5)
Requires-Dist: xarray
